jason_yang_test/__init__.py
jason_yang_test/string_utils.py
jason_yang_test/test.py
jason_yang_test-0.1.1.dist-info/LICENSE
jason_yang_test-0.1.1.dist-info/METADATA
jason_yang_test-0.1.1.dist-info/WHEEL
jason_yang_test-0.1.1.dist-info/entry_points.txt
jason_yang_test-0.1.1.dist-info/top_level.txt
jason_yang_test-0.1.1.dist-info/RECORD
