Metadata-Version: 2.1
Name: jason_yang_test
Version: 0.1.1
Summary: 一个简单的Python工具包
Home-page: https://github.com/yourusername/yang
Author: jason
Author-email: 3544909637@qq.com
Classifier: Programming Language :: Python :: 3
Classifier: License :: OSI Approved :: MIT License
Classifier: Operating System :: OS Independent
Requires-Python: >=3.6
License-File: LICENSE
